{
    "order": {
        "id": "2019000001",
        "xh": "3320121234",
        "xm": "刘玉周",
        "xb": "男",
        "csrq": "1990-1-1",
        "yx": "法学院",
        "zy": "民法学",
        "rxsj": "2008-9",
        "bysj": "2012-7",
        "lxr": "张大力",
        "lxdh": "13943216789",
        "key": "242424564abcdef8989abcdef",
        "state": 2,
        "tjsj": "2019-11-11 14:31:27",
        "xgsj": "",
        "shsj": "2019-11-12 14:31:27",
        "jfsj": "",
        "items": [{
                "productId": 0,
                "count": 3
            },
            {
                "productId": 1,
                "count": 3
            },
            {
                "productId": 2,
                "count": 3
            }
        ]
    }
}